LICENSE
README.md
setup.py
MySQL_Tool.egg-info/PKG-INFO
MySQL_Tool.egg-info/SOURCES.txt
MySQL_Tool.egg-info/dependency_links.txt
MySQL_Tool.egg-info/requires.txt
MySQL_Tool.egg-info/top_level.txt
mysql_tool/__init__.py
mysql_tool/mysql_tool.py
mysql_tool/mysql_toolp.py
test/__init__.py
test/test01.py